{"MyTeamName":"Rajasthan Royals","Name":"Yashasvi Jaiswal","Venue":"Sharjah Cricket Stadium","Date":" Sep 22 2020","OpponentTeamName":"Chennai Super Kings","Result":"Royals ","Runs":"6","Balls":"6","4s":"1","6s":"0","StrikeRate":"100.00"}{"MyTeamName":"Rajasthan Royals","Name":"Yashasvi Jaiswal","Venue":"Sharjah Cricket Stadium","Date":" Oct 9 2020","OpponentTeamName":"Delhi Capitals","Result":"Capitals ","Runs":"34","Balls":"36","Fours":"1","Six":"2","StrikeRate":"94.44"}{"MyTeamName":"Rajasthan Royals","Name":"Yashasvi Jaiswal","Venue":"Zayed Cricket Stadium, Abu Dhabi","Date":" Oct 6 2020","OpponentTeamName":"Mumbai Indians","Result":"Mum Indians ","Runs":"0","Balls":"2","Fours":"0","Six":"0","StrikeRate":"0.00"}